giveme/__init__.py
giveme/core.py
giveme/deferredproperty.py
giveme/injector.py
giveme-1.2.0.dist-info/LICENSE
giveme-1.2.0.dist-info/METADATA
giveme-1.2.0.dist-info/WHEEL
giveme-1.2.0.dist-info/top_level.txt
giveme-1.2.0.dist-info/RECORD
