Metadata-Version: 2.1
Name: giveme
Version: 1.2.0
Summary: Tiny dependency injection framework
Home-page: https://github.com/steinitzu/giveme
Author: Steinthor Palsson
Author-email: steini90@gmail.com
License: MIT
Platform: UNKNOWN
